anvil/__init__.py
anvil/cli.py
anvil/core.py
anvil/exceptions.py
anvil/VERSION
anvil/version.py
anvil-0.0.2.dist-info/DESCRIPTION.rst
anvil-0.0.2.dist-info/entry_points.txt
anvil-0.0.2.dist-info/METADATA
anvil-0.0.2.dist-info/metadata.json
anvil-0.0.2.dist-info/RECORD
anvil-0.0.2.dist-info/top_level.txt
anvil-0.0.2.dist-info/WHEEL
