Metadata-Version: 1.1
Name: anvil
Version: 0.0.2
Summary: Generates new project structures from Jinja templates
Home-page: https://github.com/dghubble/anvil
Author: Dalton Hubble
Author-email: dghubble@gmail.com
License: MIT
Keywords: anvil,generate,project,template,skeleton,package,app,plugin,jinja,jinja2
Platform: UNKNOWN
Classifier: Development Status :: 3 - Alpha
Classifier: Intended Audience :: Developers
Classifier: Topic :: Software Development :: Build Tools
Classifier: License :: OSI Approved :: MIT License
Classifier: Programming Language :: Python :: 2
Classifier: Programming Language :: Python :: 2.6
Classifier: Programming Language :: Python :: 2.7
Classifier: Programming Language :: Python :: 3
Classifier: Programming Language :: Python :: 3.2
Classifier: Programming Language :: Python :: 3.3
Classifier: Programming Language :: Python :: 3.4
